markata_gh/__about__.py
markata_gh/__init__.py
markata_gh/repo_list.py
markata_gh-0.7.0.dist-info/METADATA
markata_gh-0.7.0.dist-info/WHEEL
markata_gh-0.7.0.dist-info/entry_points.txt
markata_gh-0.7.0.dist-info/licenses/LICENSE.txt
markata_gh-0.7.0.dist-info/RECORD
