Metadata-Version: 2.1
Name: markata-gh
Version: 0.7.0
Project-URL: Documentation, https://github.com/WaylonWalker/markata-gh#readme
Project-URL: Issues, https://github.com/WaylonWalker/markata-gh/issues
Project-URL: Source, https://github.com/WaylonWalker/markata-gh
Author-email: "Waylon S. Walker" <waylon@waylonwalker.com>
Classifier: Development Status :: 4 - Beta
Classifier: Programming Language :: Python
Classifier: Programming Language :: Python :: 3.7
Classifier: Programming Language :: Python :: 3.8
Classifier: Programming Language :: Python :: 3.9
Classifier: Programming Language :: Python :: 3.10
Classifier: Programming Language :: Python :: 3.11
Classifier: Programming Language :: Python :: Implementation :: CPython
Classifier: Programming Language :: Python :: Implementation :: PyPy
Requires-Python: >=3.7
Requires-Dist: jinja2
Requires-Dist: markata
